[{"name":"Mistborn","link":"https://www.goodreads.com/series/40910-mistborn","author":""},
{"name":"Malazan","link":"https://www.goodreads.com/series/43493-malazan-book-of-the-fallen","author":""},
{"name":"Warbreaker","link":"https://www.goodreads.com/book/show/1268479.Warbreaker","author":""},
{"name":"The Emperor's Soul","link":"https://www.goodreads.com/book/show/13578175-the-emperor-s-soul","author":""},
{"name":"The Silent Patient","link":"https://www.goodreads.com/book/show/40097951-the-silent-patient","author":""},
{"name":"The Kind Worth Killing","link":"https://www.goodreads.com/book/show/21936809-the-kind-worth-killing","author":""},
{"name":"Dark Matter","link":"https://www.goodreads.com/book/show/27833670-dark-matter","author":""},
{"name":"The Wayward Pines Trilogy","link":"https://www.goodreads.com/series/116296-wayward-pines","author":""},
{"name":"The Handmaid's Tale","link":"https://www.goodreads.com/book/show/38447.The_Handmaid_s_Tale","author":""},
{"name":"Ubuntu","link":"https://www.goodreads.com/book/show/1176786.Ubuntu","author":""},
{"name":"The Umbrella Academy","link":"https://www.goodreads.com/book/show/2795053-the-umbrella-academy-vol-1","author":""},
{"name":"India After Gandhi","link":"https://www.goodreads.com/book/show/356824.India_After_Gandhi","author":""},
{"name":"Gandhi Before India","link":"https://www.goodreads.com/book/show/18310148-gandhi-before-india","author":""},
{"name":"A Corner of a Foreign Field","link":"https://www.goodreads.com/book/show/676857.A_Corner_of_a_Foreign_Field","author":""},
{"name":"Mossad","link":"https://www.goodreads.com/book/show/13623874-mossad","author":""},
{"name":"Blitzscaling","link":"https://www.goodreads.com/book/show/38398157-blitzscaling","author":""},
{"name":"Measure What Matter","link":"https://www.goodreads.com/book/show/39286958-measure-what-matters","author":""},
{"name":"Rework","link":"https://www.goodreads.com/book/show/6732019-rework","author":""},
{"name":"It doesn't have to be crazy at Work","link":"https://www.goodreads.com/book/show/38900866-it-doesn-t-have-to-be-crazy-at-work","author":""},
{"name":"Dreamers","link":"https://www.goodreads.com/book/show/37822513-dreamers","author":""},
{"name":"Geek Heresy","link":"https://www.goodreads.com/book/show/23214251-geek-heresy","author":""},
{"name":"Simon vs The Homo Sapien Agenda","link":"https://www.goodreads.com/book/show/19547856-simon-vs-the-homo-sapiens-agenda","author":""},
{"name":"The boy in the striped pyjamas","link":"https://www.goodreads.com/book/show/39999.The_Boy_in_the_Striped_Pajamas","author":""},
{"name":"The book thief","link":"https://www.goodreads.com/book/show/19063.The_Book_Thief","author":""},
{"name":"The Diary of a Young Girl","link":"https://www.goodreads.com/book/show/48855.The_Diary_of_a_Young_Girl","author":""},
{"name":"The Man in the High Castle","link":"https://www.goodreads.com/book/show/216363.The_Man_in_the_High_Castle","author":""},
{"name":"The Thrilling Adventures of Lovelace and Babbage","link":"https://www.goodreads.com/book/show/22822839-the-thrilling-adventures-of-lovelace-and-babbage","author":""},
{"name":"Mind without Fear","link":"https://www.goodreads.com/book/show/44334846-mind-without-fear","author":""},
{"name":"A Man called Ove","link":"https://www.goodreads.com/book/show/18774964-a-man-called-ove","author":""}]